{
  "updated_at": "2026-06-29 07:59",
  "articles": [
    {
      "rank": 1,
      "source": "Dev.to",
      "title": "Too cheap to be good? Think again.",
      "title_ja": "安すぎて本当に大丈夫？もう一度考え直してみて。",
      "url": "https://dev.to/pascal_cescato_692b7a8a20/too-cheap-to-be-good-think-again-4nj0",
      "likes": 81,
      "comments": 113,
      "published_at": "2026-06-23",
      "lang": "en",
      "score": 315.0,
      "summary": [
        "この記事は、安いAIサービスでも性能が良いことを伝えています。",
        "これまでの「高いものほど良い」という考え方が変わっていきます。",
        "高いお金を払わずに、誰もがAIを上手に使える未来が来そうです。"
      ],
      "highlight": "高い費用を払わなくても、AIを便利に活用できる時代がやってきました。"
    },
    {
      "rank": 2,
      "source": "note",
      "title": "①なぜ今、看護師に独立準備が必要なのか* AI時代の働き方変化",
      "title_ja": "①なぜ今、看護師に独立準備が必要なのか* AI時代の働き方変化",
      "url": "https://note.com/unlabo/n/n7130d5bb79d9",
      "likes": 0,
      "comments": 0,
      "published_at": "2026-06-28",
      "lang": "ja",
      "score": 192.0,
      "summary": [
        "AI（人工知能）の進化で、私たちの仕事のやり方が大きく変わります。",
        "看護師の仕事も例外ではなく、AIが一部の作業を助けてくれます。",
        "これからの時代は、自分らしい働き方を準備することが大切になります。"
      ],
      "highlight": "AIの進化によって、一人ひとりが自分らしく働く時代がやってきます。"
    },
    {
      "rank": 3,
      "source": "Zenn",
      "title": "AI 時代だからこそコードを読もう",
      "title_ja": "AI 時代だからこそコードを読もう",
      "url": "https://zenn.dev/chillout2san/articles/6f510abfc3fa72",
      "likes": 111,
      "comments": 0,
      "published_at": "2026-06-25",
      "lang": "ja",
      "score": 119.0,
      "summary": [
        "AI時代だからこそ、プログラムの言葉を読む力が大事だという話です。",
        "AIが作ったものの中身を理解し、もっと賢く使えるようになります。",
        "AIを使いこなしたい、すべての人が、これからの時代を楽しく生きるヒントです。"
      ],
      "highlight": "自分でプログラムを書けなくても、AIが作ったものの意味を理解し、賢く使いこなせるようになった。"
    }
  ],
  "trending_keywords": []
}